README.md
setup.py
PK.py.egg-info/PKG-INFO
PK.py.egg-info/SOURCES.txt
PK.py.egg-info/dependency_links.txt
PK.py.egg-info/top_level.txt
cmds/__init__.py