Metadata-Version: 2.1
Name: PK.py
Version: 1.0
Summary: My CMD 模組
Home-page: https://gitlab.com/moon-start/cmd.py
Author: moon-start
Author-email: login0516mp4@gmail.com
License: LGPL
Platform: UNKNOWN
